odoo/addons/mrp_bom_version/README.rst
odoo/addons/mrp_bom_version/__init__.py
odoo/addons/mrp_bom_version/__manifest__.py
odoo/addons/mrp_bom_version/data/mrp_bom_data.xml
odoo/addons/mrp_bom_version/i18n/ar.po
odoo/addons/mrp_bom_version/i18n/bg.po
odoo/addons/mrp_bom_version/i18n/bs.po
odoo/addons/mrp_bom_version/i18n/ca.po
odoo/addons/mrp_bom_version/i18n/ca_ES.po
odoo/addons/mrp_bom_version/i18n/cs.po
odoo/addons/mrp_bom_version/i18n/da.po
odoo/addons/mrp_bom_version/i18n/de.po
odoo/addons/mrp_bom_version/i18n/en_GB.po
odoo/addons/mrp_bom_version/i18n/en_US.po
odoo/addons/mrp_bom_version/i18n/es.po
odoo/addons/mrp_bom_version/i18n/es_CR.po
odoo/addons/mrp_bom_version/i18n/es_EC.po
odoo/addons/mrp_bom_version/i18n/es_ES.po
odoo/addons/mrp_bom_version/i18n/es_MX.po
odoo/addons/mrp_bom_version/i18n/es_VE.po
odoo/addons/mrp_bom_version/i18n/et.po
odoo/addons/mrp_bom_version/i18n/fi.po
odoo/addons/mrp_bom_version/i18n/fr.po
odoo/addons/mrp_bom_version/i18n/fr_CH.po
odoo/addons/mrp_bom_version/i18n/gl.po
odoo/addons/mrp_bom_version/i18n/hr.po
odoo/addons/mrp_bom_version/i18n/hr_HR.po
odoo/addons/mrp_bom_version/i18n/hu.po
odoo/addons/mrp_bom_version/i18n/id.po
odoo/addons/mrp_bom_version/i18n/it.po
odoo/addons/mrp_bom_version/i18n/ja.po
odoo/addons/mrp_bom_version/i18n/lt.po
odoo/addons/mrp_bom_version/i18n/mk.po
odoo/addons/mrp_bom_version/i18n/mn.po
odoo/addons/mrp_bom_version/i18n/mrp_bom_version.pot
odoo/addons/mrp_bom_version/i18n/nb.po
odoo/addons/mrp_bom_version/i18n/nb_NO.po
odoo/addons/mrp_bom_version/i18n/nl.po
odoo/addons/mrp_bom_version/i18n/nl_BE.po
odoo/addons/mrp_bom_version/i18n/nl_NL.po
odoo/addons/mrp_bom_version/i18n/pl.po
odoo/addons/mrp_bom_version/i18n/pt.po
odoo/addons/mrp_bom_version/i18n/pt_BR.po
odoo/addons/mrp_bom_version/i18n/pt_PT.po
odoo/addons/mrp_bom_version/i18n/ro.po
odoo/addons/mrp_bom_version/i18n/ru.po
odoo/addons/mrp_bom_version/i18n/sk.po
odoo/addons/mrp_bom_version/i18n/sl.po
odoo/addons/mrp_bom_version/i18n/sr@latin.po
odoo_addon_mrp_bom_version-16.0.1.0.0.7.dist-info/METADATA
odoo_addon_mrp_bom_version-16.0.1.0.0.7.dist-info/WHEEL
odoo_addon_mrp_bom_version-16.0.1.0.0.7.dist-info/top_level.txt
odoo_addon_mrp_bom_version-16.0.1.0.0.7.dist-info/RECORD
